{"alumno": {"1": {"name": "MIKE", "age": 14, "grade": 3, "tutor": "MARTIN", "_id": "da9dc08b807d11eba372d4bed9177ddc"}, "2": {"name": "RAMON", "age": 16, "grade": 5, "tutor": "SUSANA", "_id": "daa4c360807d11eba9c0d4bed9177ddc"}, "3": {"name": "GABRIELA", "age": 17, "grade": 6, "tutor": "MARCELA", "_id": "daa7f7b8807d11eb9715d4bed9177ddc"}, "4": {"name": "JUAN", "age": 19, "grade": 6, "tutor": "MARCELA", "_id": "daac690a807d11eb87c9d4bed9177ddc"}, "5": {"name": "LAURA", "age": 15, "grade": 4, "tutor": "DIEGO", "_id": "daaf99c3807d11eb87c1d4bed9177ddc"}, "6": {"name": "NELSON", "age": 11, "grade": 1, "tutor": "EDNA", "_id": "dabff162807d11eb9d78d4bed9177ddc"}}}